opeira/__init__.py
opeira-0.0.8.dist-info/METADATA
opeira-0.0.8.dist-info/WHEEL
opeira-0.0.8.dist-info/RECORD
